sibilate/__init__.py
sibilate/sibilate.py
sibilate-0.8.0.dist-info/entry_points.txt
sibilate-0.8.0.dist-info/LICENSE
sibilate-0.8.0.dist-info/WHEEL
sibilate-0.8.0.dist-info/METADATA
sibilate-0.8.0.dist-info/RECORD
