Metadata-Version: 2.1
Name: sibilate
Version: 0.8.0
Summary: Subtitle generator using whisper LLM
Home-page: https://github.com/datagazing/sibilate
Author: Brendan Strejcek
Author-email: brendan@datagazing.com
Requires-Python: >=3.7
Classifier: License :: OSI Approved :: MIT License
Requires-Dist: humanize
Requires-Dist: monist
Requires-Dist: tabulate
Requires-Dist: PyYAML
